lib_shop_api/__init__.py
lib_shop_api/constants.py
lib_shop_api/models.py
lib_shop_api/parser.py
lib_shop_api/urls.py
lib_shop_api-1.2.1.dist-info/METADATA
lib_shop_api-1.2.1.dist-info/WHEEL
lib_shop_api-1.2.1.dist-info/top_level.txt
lib_shop_api-1.2.1.dist-info/RECORD
