Metadata-Version: 2.4
Name: lib_shop_api
Version: 1.2.1
Summary: Library-api for web-shop
Home-page: https://github.com/YuranIgnatenko/lib_shop_api
Author: Yurij
Author-email: yuran.ignatenko@yandex.ru
Requires-Dist: requests
Requires-Dist: beautifulsoup4
Requires-Dist: fake_useragent
Dynamic: author
Dynamic: author-email
Dynamic: description
Dynamic: description-content-type
Dynamic: home-page
Dynamic: requires-dist
Dynamic: summary
